django_easy_fixture-0.3.0.dist-info/metadata.json
django_easy_fixture-0.3.0.dist-info/WHEEL
django_easy_fixture-0.3.0.dist-info/RECORD
django_easy_fixture-0.3.0.dist-info/METADATA
django_easy_fixture-0.3.0.dist-info/top_level.txt
django_easy_fixture-0.3.0.dist-info/DESCRIPTION.rst
easy_fixture/patch.py
easy_fixture/__init__.py
easy_fixture/easy_fixture.py
easy_fixture/management/__init__.py
easy_fixture/management/commands/make_fixture.py
easy_fixture/management/commands/__init__.py
