Metadata-Version: 2.0
Name: django-easy-fixture
Version: 0.3.0
Summary: easy to create a django fixture
Home-page: https://github.com/allenling/django-easy-fixture
Author: allenling
Author-email: allenling3@gmail.com
License: MIT
Keywords: fixture,django
Platform: UNKNOWN
Classifier: Development Status :: 4 - Beta
Classifier: Environment :: Web Environment
Classifier: Intended Audience :: Developers
Classifier: Framework :: Django
Classifier: Framework :: Django :: 1.8
Classifier: Framework :: Django :: 1.9
Classifier: Framework :: Django :: 1.10
Classifier: License :: OSI Approved :: MIT License
Classifier: Operating System :: OS Independent
Classifier: Programming Language :: Python
Classifier: Programming Language :: Python :: 2
Classifier: Programming Language :: Python :: 2.7
Classifier: Programming Language :: Python :: 3.5
Requires-Dist: Django (<1.10,>=1.8)
